Metadata-Version: 2.1
Name: fitbit-reader
Version: 0.0.1
Summary: A way to access Fitbit steps data
Home-page: https://github.com/robotpt/fitbit-reader
Author: Audrow Nash
Author-email: audrowna@usc.edu
License: MIT
Platform: UNKNOWN
Classifier: License :: OSI Approved :: MIT License
Classifier: Programming Language :: Python
Classifier: Programming Language :: Python :: 3
Classifier: Programming Language :: Python :: 3.6
Classifier: Programming Language :: Python :: Implementation :: CPython
Classifier: Programming Language :: Python :: Implementation :: PyPy
Requires-Python: >=3.6.0
